[
  {
    "id": "bnb-simple-flex",
    "product_name": "Simple Earn 活期 BNB",
    "category": "simple_earn_flexible",
    "source_type": "official_api",
    "source_url": "https://developers.binance.com/docs/simple_earn/Introduction",
    "asset": "BNB",
    "apr_type": "real_time",
    "apr_value": 1.82,
    "lock_days": 0,
    "liquidity_level": "high",
    "event_eligibility": [
      "launchpool",
      "hodler_airdrop"
    ],
    "risk_tier": "core",
    "confidence": 0.96,
    "deadline": null,
    "notes": "适合作为 BNB 的默认停泊位，灵活度高，也方便承接官方活动机会。"
  },
  {
    "id": "bnb-simple-locked-30d",
    "product_name": "Simple Earn 定期 BNB 30 天",
    "category": "simple_earn_locked",
    "source_type": "official_api",
    "source_url": "https://developers.binance.com/docs/simple_earn/Introduction",
    "asset": "BNB",
    "apr_type": "locked",
    "apr_value": 4.6,
    "lock_days": 30,
    "liquidity_level": "low",
    "event_eligibility": [
      "launchpool",
      "megadrop"
    ],
    "risk_tier": "core",
    "confidence": 0.95,
    "deadline": null,
    "notes": "收益更高，但对 7 天内要保留流动性的用户并不友好。"
  },
  {
    "id": "bnb-launchpool-watch",
    "product_name": "Launchpool 机会监控",
    "category": "launchpool",
    "source_type": "official_announcement",
    "source_url": "https://www.binance.com/en/support/announcement/list/48",
    "asset": "BNB",
    "apr_type": "event",
    "apr_value": 3.5,
    "lock_days": 0,
    "liquidity_level": "medium",
    "event_eligibility": [
      "launchpool"
    ],
    "risk_tier": "core",
    "confidence": 0.88,
    "deadline": "2026-03-18T23:59:00+08:00",
    "notes": "适合为当前或临近的 Launchpool 窗口保留参与弹性。"
  },
  {
    "id": "bnb-hodler-watch",
    "product_name": "HODLer 空投机会监控",
    "category": "hodler_airdrop",
    "source_type": "official_announcement",
    "source_url": "https://www.binance.com/en/support/announcement/list/128",
    "asset": "BNB",
    "apr_type": "event",
    "apr_value": 2.4,
    "lock_days": 0,
    "liquidity_level": "high",
    "event_eligibility": [
      "hodler_airdrop"
    ],
    "risk_tier": "core",
    "confidence": 0.9,
    "deadline": "2026-03-16T20:00:00+08:00",
    "notes": "更适合作为合格 BNB 持仓上的被动奖励叠加。"
  },
  {
    "id": "bnb-megadrop-watch",
    "product_name": "Megadrop 机会监控",
    "category": "megadrop",
    "source_type": "official_announcement",
    "source_url": "https://www.binance.com/en/support/announcement/list/48",
    "asset": "BNB",
    "apr_type": "event",
    "apr_value": 5.9,
    "lock_days": 30,
    "liquidity_level": "low",
    "event_eligibility": [
      "megadrop"
    ],
    "risk_tier": "advanced",
    "confidence": 0.82,
    "deadline": "2026-03-18T12:00:00+08:00",
    "notes": "潜在收益更强，但更适合接受锁仓 BNB 和主动管理时间窗口的用户。"
  },
  {
    "id": "bnb-soft-staking",
    "product_name": "软质押 BNB",
    "category": "soft_staking",
    "source_type": "official_rule",
    "source_url": "https://www.binance.com/en/earn/soft-staking",
    "asset": "BNB",
    "apr_type": "floating",
    "apr_value": 0.19,
    "lock_days": 0,
    "liquidity_level": "high",
    "event_eligibility": [],
    "risk_tier": "core",
    "confidence": 0.78,
    "deadline": null,
    "notes": "适合作为现货留仓场景下的低摩擦备选。"
  },
  {
    "id": "bnb-loan-bridge",
    "product_name": "币安借币流动性桥接",
    "category": "binance_loan",
    "source_type": "official_rule",
    "source_url": "https://www.binance.com/en/loan",
    "asset": "BNB",
    "apr_type": "borrow",
    "apr_value": 0.0,
    "lock_days": 0,
    "liquidity_level": "medium",
    "event_eligibility": [],
    "risk_tier": "advanced",
    "confidence": 0.8,
    "deadline": null,
    "notes": "当用户需要现金流但又不想完全赎回收益仓位时，可以作为高级备选。"
  },
  {
    "id": "usdt-simple-flex",
    "product_name": "Simple Earn 活期 USDT",
    "category": "simple_earn_flexible",
    "source_type": "official_api",
    "source_url": "https://developers.binance.com/docs/simple_earn/Introduction",
    "asset": "USDT",
    "apr_type": "real_time",
    "apr_value": 4.12,
    "lock_days": 0,
    "liquidity_level": "high",
    "event_eligibility": [],
    "risk_tier": "core",
    "confidence": 0.95,
    "deadline": null,
    "notes": "低风险用户的默认稳定币停泊位。"
  },
  {
    "id": "usdt-dual-investment",
    "product_name": "双币投资 USDT",
    "category": "dual_investment",
    "source_type": "official_rule",
    "source_url": "https://www.binance.com/en/dual-investment",
    "asset": "USDT",
    "apr_type": "fixed_after_subscription",
    "apr_value": 14.4,
    "lock_days": 7,
    "liquidity_level": "low",
    "event_eligibility": [],
    "risk_tier": "advanced",
    "confidence": 0.84,
    "deadline": null,
    "notes": "到期存在结算结果变化，更适合主动接受波动和转换结果的用户。"
  },
  {
    "id": "usdt-onchain-yields",
    "product_name": "链上赚币观察池",
    "category": "onchain_yields",
    "source_type": "official_rule",
    "source_url": "https://www.binance.com/en/earn/onchain-yields",
    "asset": "USDT",
    "apr_type": "variable",
    "apr_value": 9.8,
    "lock_days": 0,
    "liquidity_level": "medium",
    "event_eligibility": [],
    "risk_tier": "high_risk",
    "confidence": 0.7,
    "deadline": null,
    "notes": "收益和奖励形式更不稳定，只适合作为探索型仓位。"
  }
]
